Beetle-0.7.1.dist-info/WHEEL
Beetle-0.7.1.dist-info/DESCRIPTION.rst
Beetle-0.7.1.dist-info/entry_points.txt
Beetle-0.7.1.dist-info/RECORD
Beetle-0.7.1.dist-info/METADATA
Beetle-0.7.1.dist-info/metadata.json
Beetle-0.7.1.dist-info/top_level.txt
beetle/cli.py
beetle/renderers.py
beetle/__init__.py
beetle/base.py
beetle/builder.py
beetle/context.py
beetle/utils.py
