Metadata-Version: 2.0
Name: Beetle
Version: 0.7.1
Summary: Beetle is a simple static site generator
Home-page: https://github.com/cknv/beetle
Author: Esben Sonne
Author-email: esbensonne+code@gmail.com
License: MIT
Platform: UNKNOWN
Classifier: Development Status :: 3 - Alpha
Classifier: Environment :: Console
Classifier: Environment :: Web Environment
Classifier: Intended Audience :: Developers
Classifier: License :: OSI Approved :: MIT License
Classifier: Natural Language :: English
Classifier: Operating System :: OS Independent
Classifier: Programming Language :: Python :: 3
Classifier: Programming Language :: Python
Classifier: Topic :: Text Processing
Requires-Dist: PyYAML
Requires-Dist: awesome-slugify
Requires-Dist: Jinja2
